{"id":"richard.choi@ez-office.co.kr","config_list":[{"configName":"TEST","delete":false,"data":{"tbl_name":"TEST","tbl_info":{"tbl_name":"tbl_name","region":"first","tbl_schema":[{"No":1,"Field":"seq","Comment":null,"Type":"INT","Null":false,"primaryKey":true,"Default":null,"Formatter":"@","visible":true},{"No":2,"Field":"_nvarchar","Comment":null,"Type":"NVARCHAR(50)","Null":true,"primaryKey":false,"Default":null,"Formatter":"@","visible":true},{"No":3,"Field":"_nchar","Comment":null,"Type":"NCHAR(16)","Null":true,"primaryKey":false,"Default":null,"Formatter":"@","visible":true},{"No":4,"Field":"_datetime","Comment":null,"Type":"DATETIME","Null":true,"primaryKey":false,"Default":null,"Formatter":"YY/MM/DD","visible":true},{"No":5,"Field":"_date","Comment":null,"Type":"DATE","Null":true,"primaryKey":false,"Default":null,"Formatter":"@","visible":true},{"No":6,"Field":"_time","Comment":null,"Type":"FLOAT","Null":true,"primaryKey":false,"Default":null,"Formatter":"@","visible":true},{"No":7,"Field":"_decimal","Comment":null,"Type":"DECIMAL","Null":true,"primaryKey":false,"Default":null,"Formatter":"@","visible":true},{"No":8,"Field":"_int","Comment":null,"Type":"INT","Null":true,"primaryKey":false,"Default":null,"Formatter":"@","visible":true},{"No":9,"Field":"_bigint","Comment":null,"Type":"BIGINT","Null":true,"primaryKey":false,"Default":null,"Formatter":"@","visible":true},{"No":10,"Field":"_float","Comment":null,"Type":"FLOAT","Null":true,"primaryKey":false,"Default":null,"Formatter":"@","visible":true},{"No":11,"Field":"_money","Comment":null,"Type":"MONEY","Null":true,"primaryKey":false,"Default":null,"Formatter":"@","visible":true},{"No":12,"Field":"RegDate","Comment":null,"Type":"DATETIME","Null":true,"primaryKey":false,"Default":"([dbo].[getdate]())","Formatter":"YY/MM/DD","visible":true},{"No":13,"Field":"UpdateDate","Comment":null,"Type":"DATETIME","Null":true,"primaryKey":false,"Default":"([dbo].[getdate]())","Formatter":"YY/MM/DD","visible":true}]}}},{"configName":"e_approval_request01","delete":false,"data":{"tbl_name":"e_approval_request","tbl_info":{"tbl_name":"tbl_name","region":"first","tbl_schema":[{"No":1,"Field":"seq","Comment":null,"Type":"INT","Null":false,"primaryKey":true,"Default":null,"Formatter":"@","visible":true},{"No":2,"Field":"seqItem","Comment":null,"Type":"INT","Null":false,"primaryKey":false,"Default":null,"Formatter":"@","visible":true},{"No":3,"Field":"drafterName","Comment":null,"Type":"VARCHAR(10)","Null":false,"primaryKey":false,"Default":null,"Formatter":"@","visible":true},{"No":4,"Field":"requestType","Comment":null,"Type":"VARCHAR(20)","Null":false,"primaryKey":false,"Default":null,"Formatter":"@","visible":true},{"No":5,"Field":"requestTitle","Comment":null,"Type":"VARCHAR(64)","Null":false,"primaryKey":false,"Default":null,"Formatter":"@","visible":true},{"No":6,"Field":"requestDesc","Comment":null,"Type":"VARCHAR(512)","Null":false,"primaryKey":false,"Default":null,"Formatter":"@","visible":true},{"No":7,"Field":"signatoryNameLIst","Comment":null,"Type":"VARCHAR(20)","Null":true,"primaryKey":false,"Default":null,"Formatter":"@","visible":true},{"No":8,"Field":"priority","Comment":null,"Type":"VARCHAR(10)","Null":false,"primaryKey":false,"Default":null,"Formatter":"@","visible":true},{"No":9,"Field":"RegDate","Comment":null,"Type":"DATETIME","Null":false,"primaryKey":false,"Default":"([dbo].[getdate]())","Formatter":"YY/MM/DD","visible":true},{"No":10,"Field":"UpdateDate","Comment":null,"Type":"DATETIME","Null":false,"primaryKey":false,"Default":"([dbo].[getdate]())","Formatter":"YY/MM/DD","visible":true},{"No":99,"Field":"result","Comment":null,"Type":"VARCHAR(20)","Null":true,"primaryKey":false,"Default":null,"Formatter":"@","visible":false},{"No":99,"Field":"processDesc","Comment":null,"Type":"VARCHAR(10)","Null":true,"primaryKey":false,"Default":null,"Formatter":"@","visible":false}]}}}]}